odoo/addons/stock_picking_delivery_package_type_domain/README.rst
odoo/addons/stock_picking_delivery_package_type_domain/__init__.py
odoo/addons/stock_picking_delivery_package_type_domain/__manifest__.py
odoo/addons/stock_picking_delivery_package_type_domain/i18n/it.po
odoo/addons/stock_picking_delivery_package_type_domain/i18n/stock_picking_delivery_package_type_domain.pot
odoo/addons/stock_picking_delivery_package_type_domain/readme/CONTEXT.md
odoo/addons/stock_picking_delivery_package_type_domain/readme/CONTRIBUTORS.md
odoo/addons/stock_picking_delivery_package_type_domain/readme/DESCRIPTION.md
odoo/addons/stock_picking_delivery_package_type_domain/static/description/icon.png
odoo/addons/stock_picking_delivery_package_type_domain/static/description/index.html
odoo/addons/stock_picking_delivery_package_type_domain/tests/__init__.py
odoo/addons/stock_picking_delivery_package_type_domain/tests/common.py
odoo/addons/stock_picking_delivery_package_type_domain/tests/test_choose_delivery_package_type.py
odoo/addons/stock_picking_delivery_package_type_domain/tests/models/test.py
odoo/addons/stock_picking_delivery_package_type_domain/wizards/__init__.py
odoo/addons/stock_picking_delivery_package_type_domain/wizards/choose_delivery_package.py
odoo/addons/stock_picking_delivery_package_type_domain/wizards/choose_delivery_package.xml
odoo_addon_stock_picking_delivery_package_type_domain-18.0.1.0.0.2.dist-info/METADATA
odoo_addon_stock_picking_delivery_package_type_domain-18.0.1.0.0.2.dist-info/WHEEL
odoo_addon_stock_picking_delivery_package_type_domain-18.0.1.0.0.2.dist-info/top_level.txt
odoo_addon_stock_picking_delivery_package_type_domain-18.0.1.0.0.2.dist-info/RECORD
